{
  "EngineTransmission": {
    "Engine": ["2179 cc, 4 Cylinders Inline, 4 Valves/Cylinder, DOHC"],
    "EngineType": ["mHawk155"],
    "FuelType": ["Diesel"],
    "MaxPower": ["153 bhp @ 3750 rpm"],
    "MaxTorque": ["360 Nm @ 1750 rpm"],
    "Mileage": ["15.1 kmpl"],
    "Drivetrain": ["FWD"],
    "Transmission": ["AMT - 6 Gears, Manual Override, Sport Mode"],
    "EmissionStandard": ["BS 6"]
  },
  "DimensionWeight": {
    "Length": ["4585 mm"],
    "Width": ["1890 mm"],
    "Height": ["1785 mm"],
    "Wheelbase": ["2700 mm"],
    "GroundClearance": ["200 mm"]
  },
  "SuspensionBrakeSteering": {
    "FrontSuspension": ["MacPherson Strut with anti-roll bar"],
    "RearSuspension": ["Multi-link type with anti-roll bar"],
    "FrontBrake": ["Ventilated Disc"],
    "RearBrake": ["Disc"],
    "MinimumTurningRadius": ["5.6 m"],
    "SteeringType": ["Power assisted (Hydraulic)"],
    "Wheels": ["Alloy Wheels"],
    "SpareWheel": ["Steel"],
    "TyreSize": ["235 / 60 R18"]
  },
  "Safety": {
    "NCAPRating": ["4 Star (ANCAP)"],
    "Airbags": [
      "6 Airbags (Driver, Passenger, 2 Curtain, Driver Side, Front Passenger Side)"
    ],
    "MiddleRearSeatbelt": ["Yes"],
    "MiddleRearHeadrest": ["Yes"],
    "TyrePressureMoni": ["Yes"],
    "ChildSeatAnchor": ["No"],
    "SeatBeltWarning": ["Yes"]
  },
  "BreakindAndTraction": {
    "AntiLockBreaking": ["Yes"],
    "ElectricBrakeDistri": ["Yes"],
    "BrakeAssist": ["No"],
    "ElectricStabilityProgram": ["Yes"],
    "HillHoldControl": ["Yes"],
    "TractionControlSys": ["Yes"],
    "HillDescentControl": ["Yes"]
  },
  "LocksAndSecurity": {
    "EngineImmobilizer": ["Yes"],
    "CentralLocking": ["Keyless"],
    "SpeedSensingDoorLock": ["Yes"],
    "ChildSafetyLock": ["Yes"]
  },
  "ConfortAndCOnvenience": {
    "AirConditioner": ["Yes (Automatic Dual Zone)"],
    "FrontAC": ["Two zones, Common Fan Speed Control"],
    "RearAC": ["Yes"],
    "Heater": ["Yes"],
    "VanityMirror": ["Co-Driver"],
    "CabinBootAccess": ["Yes"],
    "AntiGlareMirrors": ["Manual Internal Only"],
    "ParkingAssist": ["Reverse Camera"],
    "ParkingSensors": ["Rear"],
    "CruiseCOntrol": ["Yes"],
    "HeadLightIgnitionONReminder": ["Yes"],
    "KeylessStartStopButton": ["Yes"],
    "SteeringAdjustment": ["Tilt & Telescopic"],
    "twelveVPowerOutlets": ["1"]
  },
  "SeatsAndUpholstery": {
    "DriverSeatAdjustment": [
      "6 way electrically adjustable (seat forward / back, backrest tilt forward / back, seat height up / down) + 2 way manually adjustable (headrest up / down)"
    ],
    "FrontPassengerSeatAdjustment": [
      "6 way manually adjustable (seat forward / back, backrest tilt forward / back, headrest up / down)"
    ],
    "RearRowSeatAdjustment": ["2 way manually adjustable (headrest up / down)"],
    "SeatUpholstery": ["Leather + Vinyl + Fabric"],
    "LeatherWrappedSteeringwheel": ["Yes"],
    "LeatherWrappedGearKnob": ["Yes"],
    "DriverArmrest": ["Yes"],
    "RearPassengerSeatsType": ["Bench"],
    "VentilatedSeats": ["No"],
    "InteriorColors": ["Premium Tan & Black"],
    "RearArmrest": ["No"],
    "FoldingRearSeat": ["Full"],
    "SplitRearSeat": ["60:40"],
    "FrontSeatbackPockets": ["Yes"],
    "HeadRest": ["Front and Rear"]
  },
  "Storage": {
    "CupHolders": ["Front & Rear"],
    "DriverArmrestStorage": ["Yes"],
    "CooledGloveBox": ["No"],
    "SunglassHOlder": ["Yes"]
  },
  "DoorsWindowsMirrorsWipers": {
    "PowerWindows": ["Front & Rear"],
    "OneTouchDown": ["Driver"],
    "OneTouchUp": ["Driver"],
    "AdjustableORVM": ["Electrically Adjustable & Retractable"],
    "TurnIndicatorsonORVM": ["Yes"],
    "RearDefogger": ["Yes"],
    "RearWiper": ["Yes"],
    "ExteriorDoorHandles": ["Body Coloured"],
    "RainSensingWipers": ["Yes"],
    "InteriorDoorHandles": ["Black"],
    "DoorPockets": ["Front & Rear"],
    "SideWindowBlinds": ["No"],
    "BootLidOpener": ["Electric Tailgate Release"],
    "OutsideRearViewMirrors": ["Body Coloured"]
  },
  "Exterior": {
    "Sunroof": ["Electrically Adjustable"],
    "RoofMountedAntenna": ["Yes"],
    "BodyColorBumpers": ["Yes"],
    "BodyKit": ["Cladding - Black/Grey"],
    "RubStrips": ["No"]
  },
  "Lighting": {
    "DaytimeRunningLights": ["Yes"],
    "AmbientInteriorLighting": ["No"],
    "PuddleLamps": ["Yes"],
    "FogLights": ["Halogen on front"],
    "HeadLights": ["Halogen Projector"],
    "AutomaticHeadLamps": ["Yes"],
    "FollowmeHomeLamps": ["Yes"],
    "TailLight": ["Halogen"],
    "CabinLamps": ["Front & Rear"],
    "HeadLightHeightAdjuster": ["Yes"],
    "GloveBoxLamp": ["Yes"],
    "LightsonVanityMirrors": ["No"],
    "RearReadingLamps": ["Yes"],
    "COrneringHeadLights": ["Passive"]
  },
  "Instrumentation": {
    "InstrumentCluster": ["Analogue-Digital"],
    "TripMeter": ["Electronic 2 trips"],
    "AverageFuelConsumption": ["Yes"],
    "AverageSpeed": ["Yes"],
    "DistanceToEmpty": ["Yes"],
    "Clock": ["Digital"],
    "LowFuelLevelWarning": ["Yes"],
    "DoorAjarWarning": ["Yes"],
    "AdjustableClusterBrightness": ["Yes"],
    "GearIndicator": ["No"],
    "ShiftIndicator": ["Yes"],
    "TachoMeter": ["Analog"],
    "InstantaneousConsumption": ["Yes"]
  },
  "EntertainmentInfoandCommunication": {
    "WirelessCharger": ["No"],
    "SmartConnectivity": ["Android Auto (Yes), Apple Car Play (Yes)"],
    "HeadUnitSize": ["No"],
    "IntegratedMusicSystem": ["Yes"],
    "Display": ["TouchScreen"],
    "GPSNavigationSystem": ["Yes"],
    "Speakers": ["6"],
    "USBCampatibility": ["Yes"],
    "AUXCompatibility": ["Yes"],
    "BluetoothCompatibility": ["Yes"],
    "SteeringMountedControls": ["Yes"],
    "VoiceCommand": ["Yes"],
    "CDPlayer": ["No"]
  },
  "ManufacturerWarranty": {
    "WarrantyYears": ["3"],
    "WarrantyKilometers": ["100000"],
    "ExtendedWarranty": ["-"]
  },
  "KeySpecification": [
    "₹ 14.27 Lakh onwards",
    "15.1 kmpl",
    "2179 cc",
    "Manual & Automatic",
    "Diesel",
    "7 Seater",
    "4,585 mm L x 1,890 mm W x 1,785 mm H"
  ],
  "SafetyFeatures": [
    "Up to six airbags",
    "Anti-lock Braking System (ABS) with Electronic Brakeforce Distribution (EBD)",
    "Electronic Stability Program (ESP) with Rollover mitigation",
    "hill hold and hill descent control",
    "disc brakes on all wheels"
  ],
  "VarientPetrol": {},
  "VarientDiesel": {
    "varient1": ["W7", "2179 cc, Manual, Diesel, 15.1 kmpl", "Rs.15.56 Lakh*"],
    "varient2": [
      "W7 AT",
      "2179 cc, Automatic, Diesel, 15.1 kmpl",
      "Rs.16.76 Lakh*"
    ],
    "varient3": ["W9", "2179 cc, Manual, Diesel, 15.1 kmpl", "Rs.17.30 Lakh*"],
    "varient4": [
      "W9 AT",
      "2179 cc, Automatic, Diesel, 15.1 kmpl",
      "Rs.18.51 Lakh*"
    ],
    "varient5": [
      "W11 Option",
      "2179 cc, Manual, Diesel, 15.1 kmpl",
      "Rs.18.84 Lakh*"
    ],
    "varient6": [
      "W11 Option AT",
      "2179 cc, Automatic, Diesel, 15.1 kmpl",
      "Rs.20.07 Lakh*"
    ]
  },
  "VarientCNG": {},

  "Mileage": {
    "mileage1": ["Petrol (1197 cc)", "Manual", "23.26 kmpl"],
    "mileage2": ["CNG (796 cc)", "Manual", "31.59 km/kg"]
  },

  "LatestUpdate": [
    "Latest Update: Mahindra has increased the prices of the XUV500 by up to Rs 4,000. Mahindra XUV500 Price: The XUV500 is now priced from Rs 15.56 lakh to Rs 20.07 lakh (ex-showroom Delhi). Mahindra XUV500 Variants: It is sold in three trims: W7, W9, and W11. Mahindra XUV500 Seating Capacity: Mahindra’s mid-size SUV can carry up to seven people. Mahindra XUV500 Engine and Transmission: It gets a 2.2-litre diesel engine (155PS/360Nm), coupled with a 6-speed manual or torque converter gearbox. Mahindra XUV500 Features: The XUV500 is equipped with a 7-inch touchscreen infotainment system with Android Auto and Apple CarPlay, a 6-way adjustable driver seat, a sunroof, and cruise control. Mahindra XUV500 Safety: Standard safety features include dual front airbags, ABS with EBD, and rear parking sensors. Mahindra XUV500 Rivals: The XUV500 locks horns with the Jeep Compass, Hyundai Tucson, Toyota Innova Crysta, MG Hector, and the Hyundai Alcazar. Mahindra XUV700: Mahindra is expected to launch the XUV700, XUV500’s spiritual successor, in August 2021."
  ],

  "ProsCons": {
    "pros": [
      "4WD option offered with both manual and automatic transmissions",
      "The XUV500 is the only SUV in its class to offer an automatic transmission with every variant except the base",
      "The XUV500 has a lot of road presence thanks to its large dimensions and muscular design"
    ],
    "cons": [
      "Petrol derivative available only with an automatic transmission",
      "Quality of some of the switches and the AC vents aren’t up to the mark, especially when you consider the price of the higher-spec variants",
      "The 4WD variant is exclusive to the top-spec W11(O) variant, which puts it out of reach for many buyers"
    ]
  },
  "Colorss": {
    "color1": ["Lake Side Brown", "bg-blue-600"],
    "color2": ["Pearl White", "bg-gray-400"],
    "color3": ["Mystic Copper", "bg-gray-400"],
    "color4": ["Moondust Silver", "bg-gray-400"],
    "color5": ["Crimson Red", "bg-gray-400"],
    "color6": ["Volcano Black", "bg-gray-400"]
  },

  "ComparisionCar": {
    "comparisioncar1": [
      "₹ 16.30 Lakh Onwards",
      "14.2 to 20.4 kmpl",
      "1493 to 1999 cc",
      "Manual & Automatic (Torque Converter)",
      "Petrol & Diesel",
      "6 & 7 Seater",
      "4,500 mm L x 1,790 mm W x 1,675 mm H",
      "https://imgd.aeplcdn.com/664x374/n/cw/ec/46812/alcazar-exterior-right-front-three-quarter.jpeg?q=85"
    ],
    "comparisioncar2": [
      "₹ 13.18 Lakh onwards",
      "13.96 to 17.41 kmpl",
      "1451 to 1956 cc",
      "Manual & Automatic",
      "Petrol & Diesel",
      "5 Seater",
      "4655 mm in length, 1835 mm in width and 1760 mm in height",
      "https://imgd.aeplcdn.com/664x374/n/cw/ec/52565/hector-exterior-right-front-three-quarter-3.jpeg?q=85"
    ]
  },

  "HighlightedFeatures": {
    "feature1": [
      "https://stimg.cardekho.com/images/carinteriorimages/930x620/Maruti/Baleno/6778/1615985207322/interior-image-209.jpg?imwidth=480",
      "Stylish Interiors",
      ""
    ],
    "feature2": [
      "https://image.shutterstock.com/image-photo/car-door-lock-knob-children-260nw-1514746379.jpg",
      "Rear Door Child Lock",
      ""
    ],
    "feature3": [
      "https://stimg.cardekho.com/images/carinteriorimages/630x420/Maruti/Alto-800/7075/1594805410865/airbags-94.jpg?tr=w-360",
      "2 Airbags",
      ""
    ]
  },
  "faqs": {
    "question1": [
      "What is the on road price of XUV500?",
      "The on-road price of XUV500 in Delhi starts at ‎₹ 17 Lakh and goes upto ‎₹ 23.77 Lakh. The on road price is made up of ex-showroom price, RTO registration, road tax and insurance amount."
    ],
    "question2": [
      "Which car is better between XUV500 and Safari?",
      "XUV500 price starts at ₹ 14.27 Lakh ex-showroom and It comes with 2179 cc engine. Whereas Safari price starts at ₹ 14.99 Lakh ex-showroom and It comes with 1956 cc engine."
    ],
    "question3": [
      "What is the mileage of Mahindra XUV500?",
      "The Mahindra XUV500 mileage is 15.1 - 15.1 kmpl."
    ]
  },

  "articles": {
    "article1": [
      "/kushaq.png",
      "Rath Yatra 2021: About 60 Skoda Kushaq SUVs To Be Delivered In Ahmedabad"
    ],
    "article2": [
      "/kushaq.png",
      "Rath Yatra 2021: About 60 Skoda Kushaq SUVs To Be Delivered In Ahmedabad"
    ],
    "article3": [
      "/kushaq.png",
      "Rath Yatra 2021: About 60 Skoda Kushaq SUVs To Be Delivered In Ahmedabad"
    ]
  },

  "SimilarCars": {},
  "ThatBrandCars": {
    "car1": [
      "https://imgd.aeplcdn.com/664x374/n/cw/ec/31883/scorpio-exterior-right-front-three-quarter-2.jpeg?q=85",
      "Scorpio",
      "₹ 12.66 Lakh onwards"
    ],
    "car2": [
      "https://imgd.aeplcdn.com/664x374/n/cw/ec/34024/xuv500-exterior-right-front-three-quarter-3.jpeg?q=85",
      "XUV 500",
      "₹ 14.27 Lakh onwards"
    ],
    "car3": [
      "https://imgd.aeplcdn.com/664x374/n/cw/ec/45933/mahindra-bolero-right-front-three-quarter1.jpeg?q=85",
      "Bolero",
      "₹ 8.64 Lakh onwards"
    ],
    "car4": [
      "https://imgd.aeplcdn.com/664x374/n/cw/ec/33266/alturas-g4-exterior-right-front-three-quarter-2.jpeg?q=85",
      "Alturas G4",
      "₹ 28.77 Lakh onwards"
    ],
    "car5": [
      "https://imgd.aeplcdn.com/664x374/n/cw/ec/21497/kuv100-nxt-exterior-right-front-three-quarter-64047.jpeg?q=85",
      "Kuv 100",
      "₹ 6.10 Lakh onwards"
    ],
    "car6": [
      "https://imgd.aeplcdn.com/664x374/n/cw/ec/49114/marazzo-exterior-right-front-three-quarter-4.jpeg?q=85",
      "Marazzo",
      "₹ 12.30 Lakh onwards"
    ],
    "car7": [
      "https://imgd.aeplcdn.com/664x374/n/cw/ec/40087/thar-exterior-right-front-three-quarter-11.jpeg?q=85",
      "Thar",
      "₹ 12.78 Lakh onwards"
    ],
    "car8": [
      "https://imgd.aeplcdn.com/664x374/n/cw/ec/26918/xuv300-exterior-right-front-three-quarter-148706.jpeg?q=85",
      "Xuv 300",
      "₹ 7.96 Lakh onwards"
    ],
    "car9": [
      "https://imgd.aeplcdn.com/664x374/n/cw/ec/97853/bolero-neo-exterior-right-front-three-quarter-2.jpeg?q=85",
      "Bolero Neo",
      "₹ 8.48 Lakh onwards"
    ]
  },

  "UpcommingCarBrand": {
    "car1": [
      "https://imgd.aeplcdn.com/664x374/n/cw/ec/42355/xuv700-exterior-left-front-three-quarter.jpeg?isig=0&q=85",
      "XUV 700",
      "₹ 13.00 - 20.00 Lakh"
    ],
    "car2": [
      "https://imgd.aeplcdn.com/664x374/cw/ec/41157/Mahindra-TUV300-Plus-Facelift-Exterior-163347.jpg?wm=0&q=85",
      "TUV 300 Plus",
      "₹ 10.00 - 12.00 Lakh"
    ],
    "car3": [
      "https://imgd.aeplcdn.com/664x374/cw/ec/33297/Mahindra-e20-NXT-Exterior-120569.jpg?wm=0&q=85",
      "e20 NXT",
      "₹ 6.00 - 8.00 Lakh"
    ],
    "car4": [
      "https://imgd.aeplcdn.com/664x374/cw/ec/42453/Mahindra-S204-Exterior-171413.jpg?wm=0&q=85",
      "Mahindra S204",
      "₹ 11.00 - 15.00 Lakh"
    ],
    "car5": [
      "https://imgd.aeplcdn.com/664x374/n/cw/ec/45278/mahindra-exuv300-left-side-view0.jpeg?q=85",
      "eXUV300",
      "₹ 14.00 - 16.00 Lakh"
    ],
    "car6": [
      "https://imgd.aeplcdn.com/664x374/cw/ec/40432/Mahindra-New-Scorpio-Exterior-159617.jpg?wm=0&q=85",
      "New Scorpio",
      "₹ 10.00 - 14.00 Lakh"
    ],
    "car7": [
      "https://imgd.aeplcdn.com/664x374/cw/ec/33261/Mahindra-eKUV100-Exterior-170053.jpg?wm=0&q=85",
      "eKUV100",
      "₹ 8.00 - 9.00 Lakh"
    ]
  },
  "CarInfo": {
    "CompanyName": "Mahindra",
    "CarName": "Mahindra Xuv500",
    "OnlyName": ["Xuv500"],
    "Price": ["₹ 14.27 Lakh"],
    "TopPic": ["https://i.ibb.co/D5F3qVf/xuv500.png"],
    "ThumPic": "https://i.ibb.co/x8dWZbQ/xuv5001630474669.jpg",
    "CarFullName": ["Mahindra Xuv500"]
  }
}
