{
  "EngineTransmission": {
    "Engine": ["2494 cc, 4 Cylinders In V Shape, 4 Valves/Cylinder, DOHC"],
    "EngineType": ["Petrol Hybrid"],
    "FuelType": ["Hybrid (Electric + Petrol)"],
    "MaxPower": ["115 bhp @ 4700 rpm"],
    "MaxTorque": ["198 Nm @ 2800 rpm"],
    "Mileage": ["-"],
    "Drivetrain": ["FWD"],
    "Transmission": ["Automatic (Dual Clutch) - CVT Gears"],
    "EmissionStandard": ["BS 6"]
  },
  "DimensionWeight": {
    "Length": ["4935 mm"],
    "Width": ["1850 mm"],
    "Height": ["1895 mm"],
    "Wheelbase": ["3000 mm"],
    "GroundClearance": ["-"]
  },
  "SuspensionBrakeSteering": {
    "FrontSuspension": ["MCPherson Strut with Stabiliser"],
    "RearSuspension": ["Multi-Link Double Wishbone with Stabiliser"],
    "FrontBrake": ["Disc"],
    "RearBrake": ["Disc"],
    "MinimumTurningRadius": ["-"],
    "SteeringType": ["Power assisted (Electric)"],
    "Wheels": ["Alloy Wheels"],
    "SpareWheel": ["Alloy"],
    "TyreSize": ["225 / 60 R17"]
  },
  "Safety": {
    "NCAPRating": ["5 Star (ANCAP)"],
    "Airbags": [
      "7 Airbags (Driver, Passenger, 2 Curtain, Driver Knee, Driver Side, Front Passenger Side)"
    ],
    "MiddleRearSeatbelt": ["No"],
    "MiddleRearHeadrest": ["Yes"],
    "TyrePressureMoni": ["Yes"],
    "ChildSeatAnchor": ["Yes"],
    "SeatBeltWarning": ["Yes"]
  },
  "BreakindAndTraction": {
    "AntiLockBreaking": ["Yes"],
    "ElectricBrakeDistri": ["Yes"],
    "BrakeAssist": ["Yes"],
    "ElectricStabilityProgram": ["Yes"],
    "HillHoldControl": ["Yes"],
    "TractionControlSys": ["Yes"],
    "HillDescentControl": ["No"]
  },
  "LocksAndSecurity": {
    "EngineImmobilizer": ["Yes"],
    "CentralLocking": ["Keyless"],
    "SpeedSensingDoorLock": ["Yes"],
    "ChildSafetyLock": ["Yes"]
  },
  "ConfortAndCOnvenience": {
    "AirConditioner": ["Yes (Automatic)"],
    "FrontAC": ["Two Zone, Common Fan Speed Control"],
    "RearAC": ["Separate Zone, Vents on Roof , Individual Fan Speed Controls"],
    "Heater": ["Yes"],
    "VanityMirror": ["Driver & Co-Driver"],
    "CabinBootAccess": ["Yes"],
    "AntiGlareMirrors": ["Electronic - Internal Only"],
    "ParkingAssist": ["Reverse Camera"],
    "ParkingSensors": ["Front & Rear"],
    "CruiseCOntrol": ["Yes"],
    "HeadLightIgnitionONReminder": ["Yes"],
    "KeylessStartStopButton": ["Yes"],
    "SteeringAdjustment": ["Manual Tilt & Telescopic"],
    "twelveVPowerOutlets": ["1"]
  },
  "SeatsAndUpholstery": {
    "DriverSeatAdjustment": [
      "8 way electrically adjustable (seat forward / back, backrest tilt forward / back, seat height up / down, seat base angle up / down) + 2 way manually adjustable (headrest up / down)"
    ],
    "FrontPassengerSeatAdjustment": [
      "6 way electrically adjustable (seat forward / back, backrest tilt forward / back, seat base angle up / down) + 2 way manually adjustable (headrest up / down)"
    ],
    "RearRowSeatAdjustment": [
      "4 way electrically adjustable with 2 memory presets (seat forward / back, backrest tilt forward / back) + 2 way manually adjustable (headrest up / down)"
    ],
    "SeatUpholstery": ["Leather"],
    "LeatherWrappedSteeringwheel": ["Yes"],
    "LeatherWrappedGearKnob": ["Yes"],
    "DriverArmrest": ["Yes"],
    "RearPassengerSeatsType": ["Captain Seats"],
    "VentilatedSeats": ["Front and Middle Row"],
    "InteriorColors": ["Beige"],
    "RearArmrest": ["Yes"],
    "FoldingRearSeat": ["Full"],
    "SplitRearSeat": ["50:50 split"],
    "FrontSeatbackPockets": ["Yes"],
    "HeadRest": ["Front & Rear"]
  },
  "Storage": {
    "CupHolders": ["Front & Rear"],
    "DriverArmrestStorage": ["Yes"],
    "CooledGloveBox": ["Yes"],
    "SunglassHOlder": ["Yes"]
  },
  "DoorsWindowsMirrorsWipers": {
    "PowerWindows": ["Front & Rear"],
    "OneTouchDown": ["All"],
    "OneTouchUp": ["All"],
    "AdjustableORVM": ["Electrical Adjustable"],
    "TurnIndicatorsonORVM": ["Yes"],
    "RearDefogger": ["Yes"],
    "RearWiper": ["Yes"],
    "ExteriorDoorHandles": ["Chrome"],
    "RainSensingWipers": ["No"],
    "InteriorDoorHandles": ["Chrome"],
    "DoorPockets": ["Front & Rear"],
    "SideWindowBlinds": ["No"],
    "BootLidOpener": ["Internal with Remote"],
    "OutsideRearViewMirrors": ["Body Coloured"]
  },
  "Exterior": {
    "Sunroof": ["Electrically Adjustable"],
    "RoofMountedAntenna": ["No"],
    "BodyColorBumpers": ["Yes"],
    "BodyKit": ["No"],
    "RubStrips": ["No"]
  },
  "Lighting": {
    "DaytimeRunningLights": ["Yes"],
    "AmbientInteriorLighting": ["Yes"],
    "PuddleLamps": ["Yes"],
    "FogLights": ["LED"],
    "HeadLights": ["LED"],
    "AutomaticHeadLamps": ["Yes"],
    "FollowmeHomeLamps": ["Yes"],
    "TailLight": ["LED"],
    "CabinLamps": ["Front & Rear"],
    "HeadLightHeightAdjuster": ["Yes"],
    "GloveBoxLamp": ["Yes"],
    "LightsonVanityMirrors": ["Driver & Co-Driver"],
    "RearReadingLamps": ["Yes"],
    "COrneringHeadLights": ["No"]
  },
  "Instrumentation": {
    "InstrumentCluster": ["Analogue and Digital"],
    "TripMeter": ["Electronic 2 trips"],
    "AverageFuelConsumption": ["Yes"],
    "AverageSpeed": ["Yes"],
    "DistanceToEmpty": ["Yes"],
    "Clock": ["Digital"],
    "LowFuelLevelWarning": ["Yes"],
    "DoorAjarWarning": ["Yes"],
    "AdjustableClusterBrightness": ["Yes"],
    "GearIndicator": ["Yes"],
    "ShiftIndicator": ["Yes"],
    "TachoMeter": ["Analogue"],
    "InstantaneousConsumption": ["Yes"]
  },
  "EntertainmentInfoandCommunication": {
    "WirelessCharger": ["Yes"],
    "SmartConnectivity": ["Android Auto (Yes), Apple Car Play (Yes)"],
    "HeadUnitSize": ["-"],
    "IntegratedMusicSystem": ["Yes"],
    "Display": ["TouchScreen"],
    "GPSNavigationSystem": ["Yes"],
    "Speakers": ["6+"],
    "USBCampatibility": ["Yes"],
    "AUXCompatibility": ["Yes"],
    "BluetoothCompatibility": ["Yes"],
    "SteeringMountedControls": ["Yes"],
    "VoiceCommand": ["Yes"],
    "CDPlayer": ["No"]
  },
  "ManufacturerWarranty": {
    "WarrantyYears": ["3"],
    "WarrantyKilometers": ["100000"],
    "ExtendedWarranty": ["-"]
  },
  "KeySpecification": [
    "₹ 89.89 Lakh onwards",
    "16.35 kmpl",
    "2494 cc",
    "Automatic (Dual Clutch)",
    "Hybrid (Electric + Petrol)",
    "7 Seater",
    "4,935 mm L x 1,850 mm W x 1,895 mm H"
  ],
  "SafetyFeatures": [
    " Pre-Collision System (PCS)",
    "Lane Tracing Assist (LTA)",
    "Dynamic Radar Cruise Control (DRCC) for All Speeds.",
    "Automatic High Beam (AHB)",
    "Electric Parking Brake (EPB) with Brake Hold.",
    "Blind Spot Monitor (BSM)",
    "Front and Rear Digital Video Recorder (DVR)",
    "Panoramic View Monitor (PVM)"
  ],
  "VarientPetrol": {
    "varient1": [
      "Executive Lounge",
      "2494 cc, Automatic, Petrol, 16.35 kmpl",
      "Rs.89.90 Lakh*"
    ]
  },
  "VarientDiesel": {},
  "VarientCNG": {},

  "Mileage": {
    "mileage1": ["Petrol (1197 cc)", "Manual", "23.26 kmpl"],
    "mileage2": ["CNG (796 cc)", "Manual", "31.59 km/kg"]
  },

  "LatestUpdate": [
    "Latest Update: Toyota has increased the price of the Vellfire. Toyota Vellfire Variant: The Vellfire is offered in a single fully-loaded Executive Lounge variant. Toyota Vellfire Price: It is priced at Rs 83.50 lakh (ex-showroom). Toyota Vellfire Powertrain: The luxury MPV is powered by a BS6-compliant 2.5-litre petrol-hybrid engine that puts out 180PS and 235Nm. It also features a 4WD system and comes paired to a CVT gearbox. Toyota Vellfire Features: Toyota offers the Vellfire with heated and ventilated memory seats with an Ottoman full-recline function, twin sunroof, sunshades, ambient lighting, and automatic climate control.  Toyota Vellfire Safety: It gets seven airbags, vehicle dynamic management, a panoramic view monitor, and front and rear parking sensors. Toyota Vellfire Rivals: The Toyota Vellfire goes up against the Mercedes-Benz V-Class."
  ],

  "ProsCons": {
    "pros": [
      "Luxurious second row seats like no other",
      "Powered adjust for recline, foot rest and even footrest extension",
      "Enough space to seat even the tallest of individuals"
    ],
    "cons": [
      "Costs nearly a crore",
      "No charging sockets or ports for the second and third row",
      "Ride quality will be a bit stiff"
    ]
  },
  "Colorss": {
    "color1": ["Pearl White", "bg-brown-800"],
    "color2": ["Graphite", "bg-gray-900"],
    "color3": ["BURNING BLACK", "bg-yellow-900"],
    "color4": ["Black", "bg-gray-100"]
  },

  "ComparisionCar": {
    "comparisioncar1": [
      "₹ 71.10 Lakh Onwards",
      "16 kmpl",
      "1950 cc",
      "Automatic",
      "Diesel",
      "7 Seater",
      "5,140-5,370 mm L x 1,928 mm W x 1,901-1,909 mm H",
      "https://imgd.aeplcdn.com/664x374/cw/ec/37616/MercedesBenz-VClass-Right-Front-Three-Quarter-147184.jpg?wm=0&q=85"
    ],
    "comparisioncar2": [
      "₹ 24.95 Lakh",
      "14 kmpl",
      "2199 cc",
      "Automatic (Torque Converter)",
      "Diesel",
      "6 & 7 Seater",
      "5,115 mm L x 1,985 mm W x 1,740-1,755 mm H",
      "https://imgd.aeplcdn.com/664x374/n/cw/ec/41205/kia-carnival-right-front-three-quarter8.jpeg?q=85"
    ]
  },

  "HighlightedFeatures": {
    "feature1": [
      "https://stimg.cardekho.com/images/carinteriorimages/930x620/Maruti/Baleno/6778/1615985207322/interior-image-209.jpg?imwidth=480",
      "Stylish Interiors",
      ""
    ],
    "feature2": [
      "https://image.shutterstock.com/image-photo/car-door-lock-knob-children-260nw-1514746379.jpg",
      "Rear Door Child Lock",
      ""
    ],
    "feature3": [
      "https://stimg.cardekho.com/images/carinteriorimages/630x420/Maruti/Alto-800/7075/1594805410865/airbags-94.jpg?tr=w-360",
      "2 Airbags",
      ""
    ]
  },
  "faqs": {
    "question1": [
      "What is the on road price of Vellfire?",
      "The on-road price of Vellfire in Delhi is ₹ 1.03 Crore. The on road price is made up of ex-showroom price, RTO registration, road tax and insurance amount."
    ],
    "question2": [
      "Which car is better between Vellfire and V-Class?",
      "Vellfire price starts at ₹ 89.89 Lakh ex-showroom and It comes with 2494 cc engine. Whereas V-Class price starts at ₹ 71.10 Lakh ex-showroom and It comes with 2143 cc engine."
    ],
    "question3": [
      "What is the mileage of Toyota Vellfire?",
      "The Toyota Vellfire mileage is 16.35 kmpl."
    ]
  },

  "articles": {
    "article1": [
      "/kushaq.png",
      "Rath Yatra 2021: About 60 Skoda Kushaq SUVs To Be Delivered In Ahmedabad"
    ],
    "article2": [
      "/kushaq.png",
      "Rath Yatra 2021: About 60 Skoda Kushaq SUVs To Be Delivered In Ahmedabad"
    ],
    "article3": [
      "/kushaq.png",
      "Rath Yatra 2021: About 60 Skoda Kushaq SUVs To Be Delivered In Ahmedabad"
    ]
  },

  "SimilarCars": {},
  "ThatBrandCars": {
    "car1": [
      "https://imgd.aeplcdn.com/664x374/n/cw/ec/51435/innova-crysta-exterior-right-front-three-quarter-3.jpeg?q=85",
      "Innova",
      "₹ 16.82 Lakh onwards"
    ],
    "car2": [
      "https://imgd.aeplcdn.com/664x374/n/cw/ec/44709/fortuner-exterior-right-front-three-quarter-19.jpeg?q=85",
      "Fortuner",
      "₹ 30.36 Lakh onwards"
    ],
    "car3": [
      "https://imgd.aeplcdn.com/664x374/n/cw/ec/47016/urban-cruiser-exterior-right-front-three-quarter.jpeg?q=85",
      "Urban Cruiser",
      "₹ 8.63 Lakh onwards"
    ],
    "car4": [
      "https://imgd.aeplcdn.com/664x374/n/cw/ec/39545/glanza-exterior-right-front-three-quarter-159523.jpeg?q=85",
      "Glanza",
      "₹ 7.34 Lakh onwards"
    ],
    "car5": [
      "https://imgd.aeplcdn.com/664x374/n/cw/ec/32943/yaris-exterior-right-front-three-quarter-2.jpeg?q=85",
      "Yaris",
      "₹ 9.17 Lakh onwards"
    ],
    "car6": [
      "https://imgd.aeplcdn.com/664x374/n/cw/ec/41217/toyota-vellfire-right-front-three-quarter5.jpeg?q=85",
      "Vellfire",
      "₹ 89.89 Lakh onwards"
    ],
    "car7": [
      "https://imgd.aeplcdn.com/664x374/cw/ec/37561/Toyota-Camry-Right-Front-Three-Quarter-146683.jpg?wm=0&q=85",
      "Camry",
      "₹ 40.61 Lakh onwards"
    ]
  },

  "UpcommingCarBrand": {
    "car1": [
      "https://stimg.cardekho.com/images/carexteriorimages/630x420/Toyota/Hilux/8445/1622783707227/front-left-side-47.jpg?imwidth=420&impolicy=resize",
      "Hilux",
      "Rs.18.00 Lakh*"
    ],
    "car2": [
      "https://stimg.cardekho.com/images/carexteriorimages/630x420/Toyota/Land-Cruiser/8448/1623313668941/front-left-side-47.jpg?tr=w-456",
      "Land Cruiser",
      "Rs.1.50 Cr*"
    ]
  },
  "Thatbrandmobile": [
    {
      "ccard": [
        "https://i.ibb.co/CVtGrTZ/innova1630474668.jpg",
        "Innova",
        "₹ 16.82 Lakh onwards"
      ]
    },
    {
      "ccard": [
        "https://i.ibb.co/DkDwYyq/fortuner1630474667.jpg",
        "Fortuner",
        "₹ 30.36 Lakh onwards"
      ]
    },
    {
      "ccard": [
        "https://i.ibb.co/rsLSWr6/urbancruiser1630474669.jpg",
        "Urban Cruiser",
        "₹ 8.63 Lakh onwards"
      ]
    },
    {
      "ccard": [
        "https://i.ibb.co/ZY5C0px/glanza1630474668.jpg",
        "Glanza",
        "₹ 7.34 Lakh onwards"
      ]
    },
    {
      "ccard": [
        "https://i.ibb.co/BZZVKJ4/yaris1630474669.jpg",
        "Yaris",
        "₹ 9.17 Lakh onwards"
      ]
    },
    {
      "ccard": [
        "https://i.ibb.co/tPKSLcr/vellfire1630474669.jpg",
        "Vellfire",
        "₹ 89.89 Lakh onwards"
      ]
    },
    {
      "ccard": [
        "https://i.ibb.co/g37fTZq/camry1630474667.jpg",
        "Camry",
        "₹ 40.61 Lakh onwards"
      ]
    }
  ],
  "CarInfo": {
    "CompanyName": "Toyota",
    "CarName": "Toyota Vellfire",
    "OnlyName": ["Vellfire"],
    "Price": ["₹ 89.89 Lakh"],
    "TopPic": ["https://i.ibb.co/c86Y9D6/vellfire.webp"],
    "ThumPic": "https://i.ibb.co/tPKSLcr/vellfire1630474669.jpg",
    "CarFullName": ["Toyota Vellfire"]
  }
}
