{
  "EngineTransmission": {
    "Engine": ["1956 cc, 4 Cylinders Inline, 4 Valves/Cylinder, DOHC"],
    "EngineType": ["2.0 L Kryotec"],
    "FuelType": ["Diesel"],
    "MaxPower": ["168 bhp @ 3750 rpm"],
    "MaxTorque": ["350 Nm @ 1750 rpm"],
    "Mileage": ["14.08 kmpl"],
    "Drivetrain": ["FWD"],
    "Transmission": [
      "Automatic (Torque Converter) - 6 Gears, Manual Override, Sport Mode"
    ],
    "EmissionStandard": ["BS 6"]
  },
  "DimensionWeight": {
    "Length": ["4661 mm"],
    "Width": ["1894 mm"],
    "Height": ["1786 mm"],
    "Wheelbase": ["2741 mm"],
    "GroundClearance": ["205 mm"]
  },
  "SuspensionBrakeSteering": {
    "FrontSuspension": [
      "Independent, Lower Wishbone, McPherson Strut with Coil Spring & Anti Roll Bar"
    ],
    "RearSuspension": [
      "Semi Independent Twist Blade with Panhard Rod and Coil Spring"
    ],
    "FrontBrake": ["Disc"],
    "RearBrake": ["Disc"],
    "MinimumTurningRadius": ["-"],
    "SteeringType": ["Power assisted (Electric)"],
    "Wheels": ["Alloy Wheels"],
    "SpareWheel": ["Steel"],
    "TyreSize": ["235 / 60 R18"]
  },
  "Safety": {
    "NCAPRating": ["Not Tested"],
    "Airbags": [
      "6 Airbags (Driver, Passenger, 2 Curtain, Driver Side, Front Passenger Side)"
    ],
    "MiddleRearSeatbelt": ["No"],
    "MiddleRearHeadrest": ["No"],
    "TyrePressureMoni": ["Yes"],
    "ChildSeatAnchor": ["Yes"],
    "SeatBeltWarning": ["Yes"]
  },
  "BreakindAndTraction": {
    "AntiLockBreaking": ["Yes"],
    "ElectricBrakeDistri": ["Yes"],
    "BrakeAssist": ["Yes"],
    "ElectricStabilityProgram": ["Yes"],
    "HillHoldControl": ["Yes"],
    "TractionControlSys": ["Yes"],
    "HillDescentControl": ["Yes"]
  },
  "LocksAndSecurity": {
    "EngineImmobilizer": ["Yes"],
    "CentralLocking": ["Keyless"],
    "SpeedSensingDoorLock": ["Yes"],
    "ChildSafetyLock": ["Yes"]
  },
  "ConfortAndCOnvenience": {
    "AirConditioner": ["Yes (Automatic)"],
    "FrontAC": ["Single Zone, Common Fan Speed Control"],
    "RearAC": ["Blower, Vents on Pillars"],
    "Heater": ["Yes"],
    "VanityMirror": ["Co-Driver"],
    "CabinBootAccess": ["Yes"],
    "AntiGlareMirrors": ["Electronic - Internal Only"],
    "ParkingAssist": ["Reverse Camera"],
    "ParkingSensors": ["Rear"],
    "CruiseCOntrol": ["Yes"],
    "HeadLightIgnitionONReminder": ["Yes"],
    "KeylessStartStopButton": ["Yes"],
    "SteeringAdjustment": ["Manual Tilt & Telescopic"],
    "twelveVPowerOutlets": ["1"]
  },
  "SeatsAndUpholstery": {
    "DriverSeatAdjustment": [
      "6 way manually adjustable (seat forward / back, backrest tilt forward / back, headrest up / down)"
    ],
    "FrontPassengerSeatAdjustment": [
      "6 way manually adjustable (seat forward / back, backrest tilt forward / back, headrest up / down)"
    ],
    "RearRowSeatAdjustment": [
      "4 way manually adjustable (seat forward / back, headrest up / down)"
    ],
    "SeatUpholstery": ["Leather"],
    "LeatherWrappedSteeringwheel": ["Yes"],
    "LeatherWrappedGearKnob": ["Yes"],
    "DriverArmrest": ["Yes"],
    "RearPassengerSeatsType": ["Bench"],
    "VentilatedSeats": ["No"],
    "InteriorColors": ["Black"],
    "RearArmrest": ["Yes"],
    "FoldingRearSeat": ["Full"],
    "SplitRearSeat": ["60:40 split"],
    "FrontSeatbackPockets": ["Yes"],
    "HeadRest": ["Front & Rear"]
  },
  "Storage": {
    "CupHolders": ["Front, Second & Third"],
    "DriverArmrestStorage": ["Yes"],
    "CooledGloveBox": ["Yes"],
    "SunglassHOlder": ["Yes"]
  },
  "DoorsWindowsMirrorsWipers": {
    "PowerWindows": ["Front & Rear"],
    "OneTouchDown": ["Driver"],
    "OneTouchUp": ["Driver"],
    "AdjustableORVM": ["Electrical Adjustable"],
    "TurnIndicatorsonORVM": ["Yes"],
    "RearDefogger": ["Yes"],
    "RearWiper": ["Yes"],
    "ExteriorDoorHandles": ["Gloss Black"],
    "RainSensingWipers": ["Yes"],
    "InteriorDoorHandles": ["Chrome"],
    "DoorPockets": ["Front & Rear"],
    "SideWindowBlinds": ["No"],
    "BootLidOpener": ["Electric Tailgate Release"],
    "OutsideRearViewMirrors": ["Black"]
  },
  "Exterior": {
    "Sunroof": ["Panoramic Sunroof"],
    "RoofMountedAntenna": ["Yes"],
    "BodyColorBumpers": ["Yes"],
    "BodyKit": ["Cladding - Black/Grey"],
    "RubStrips": ["No"]
  },
  "Lighting": {
    "DaytimeRunningLights": ["Yes"],
    "AmbientInteriorLighting": ["Multi-Colour"],
    "PuddleLamps": ["Yes"],
    "FogLights": ["Halogen"],
    "HeadLights": ["Bi-Xenon Projector"],
    "AutomaticHeadLamps": ["Yes"],
    "FollowmeHomeLamps": ["Yes"],
    "TailLight": ["LED"],
    "CabinLamps": ["Front & Rear"],
    "HeadLightHeightAdjuster": ["Yes"],
    "GloveBoxLamp": ["Yes"],
    "LightsonVanityMirrors": ["Co-Driver"],
    "RearReadingLamps": ["Yes"],
    "COrneringHeadLights": ["Passive"]
  },
  "Instrumentation": {
    "InstrumentCluster": ["Analogue and Digital"],
    "TripMeter": ["Electronic 2 trips"],
    "AverageFuelConsumption": ["Yes"],
    "AverageSpeed": ["Yes"],
    "DistanceToEmpty": ["Yes"],
    "Clock": ["Digital"],
    "LowFuelLevelWarning": ["Yes"],
    "DoorAjarWarning": ["Yes"],
    "AdjustableClusterBrightness": ["Yes"],
    "GearIndicator": ["No"],
    "ShiftIndicator": ["No"],
    "TachoMeter": ["Digital"],
    "InstantaneousConsumption": ["Yes"]
  },
  "EntertainmentInfoandCommunication": {
    "WirelessCharger": ["No"],
    "SmartConnectivity": ["Android Auto (Yes), Apple Car Play (Yes)"],
    "HeadUnitSize": ["-"],
    "IntegratedMusicSystem": ["Yes"],
    "Display": ["TouchScreen"],
    "GPSNavigationSystem": ["Yes"],
    "Speakers": ["6+"],
    "USBCampatibility": ["Yes"],
    "AUXCompatibility": ["Yes"],
    "BluetoothCompatibility": ["Yes"],
    "SteeringMountedControls": ["Yes"],
    "VoiceCommand": ["Yes"],
    "CDPlayer": ["No"]
  },
  "ManufacturerWarranty": {
    "WarrantyYears": ["2"],
    "WarrantyKilometers": ["100000"],
    "ExtendedWarranty": ["-"]
  },
  "KeySpecification": [
    "₹ 14.99 Lakh onwards",
    "14.08 to 16.14 kmpl",
    "1956 cc",
    "Manual & Automatic (Torque Converter)",
    "Diesel",
    "7 Seater",
    "4,661 mm L x 1,894 mm W x 1,786 mm H"
  ],
  "SafetyFeatures": [
    "6 airbags",
    "ABS with EBD and CSC",
    "reverse parking sensors",
    "ISOFIX",
    "driver and co-driver seatbelt reminder",
    "high-speed alert system",
    "impact sensing auto door unlock."
  ],
  "VarientPetrol": {},
  "VarientDiesel": {
    "varient1": [
      "XE",
      "1956  cc, Manual, Diesel, 16.14 kmpl",
      "Rs.14.99 Lakh*"
    ],
    "varient2": [
      "XM",
      "1956  cc, Manual, Diesel, 16.14 kmpl",
      "Rs.16.36 Lakh*"
    ],
    "varient3": ["XT", "1956 cc, Manual, Diesel, 16.14 kmpl", "Rs.17.61 Lakh*"],
    "varient4": [
      "XT Plus",
      "1956 cc, Manual, Diesel, Rs.18.61 Lakh*",
      "Rs.17.81 Lakh*"
    ],
    "varient5": [
      "XZ",
      "1956  cc, Manual, Diesel, 16.14 kmpl",
      "Rs.19.51 Lakh*"
    ],
    "varient6": [
      "XZ Plus",
      "1956 cc, Manual, Diesel, 16.14 kmpl",
      "Rs.20.35 Lakh*"
    ],
    "varient7": [
      "XZ Plus 6 Str",
      "1956 cc, Manual, Diesel, 16.14 kmpl",
      "Rs.20.37 Lakh*"
    ],
    "varient8": [
      "XZ Plus Adventure Edition",
      "1956 cc, Manual, Diesel, 16.14 kmpl",
      "Rs.20.56 Lakh*"
    ],
    "varient9": [
      "XZ Plus 6 Str Adventure Edition",
      "1956 cc, Manual, Diesel, 16.14 kmpl",
      "Rs.20.58 Lakh*"
    ],
    "varient10": [
      "XZA AT",
      "1956 cc, Automatic, Diesel, 14.08 kmpl",
      "Rs.20.76 Lakh*"
    ],
    "varient11": [
      "XZA Plus AT",
      "1956 cc, Automatic, Diesel, 14.08 kmpl",
      "Rs.21.61 Lakh*"
    ],
    "varient12": [
      "XZA Plus 6 Str AT",
      "1956 cc, Automatic, Diesel, 14.08 kmpl",
      "Rs.21.65 Lakh*"
    ],
    "varient13": [
      "XZA Plus Adventure Edition AT",
      "1956 cc, Automatic, Diesel, 14.08 kmpl",
      "Rs.21.81 Lakh*"
    ],
    "varient14": [
      "XZA Plus 6Str Adventure Edition AT",
      "1956 cc, Automatic, Diesel, 14.08 kmpl",
      "Rs.21.86 Lakh*"
    ]
  },
  "VarientCNG": {},

  "Mileage": {
    "mileage1": ["Petrol (1197 cc)", "Manual", "23.26 kmpl"],
    "mileage2": ["CNG (796 cc)", "Manual", "31.59 km/kg"]
  },

  "LatestUpdate": [
    "Latest Update: Tata has rolled out the 10,000th Safari from its Pune facility. Tata Safari Price: The SUV is priced from Rs 14.99 lakh to Rs 21.81 lakh (ex-showroom). Tata Safari Variants: It is sold in six trims: XE, XM, XT, XT+, XZ, and XZ+. Tata Safari Seating Capacity: The Safari is available in both 6- and 7-seater configurations. The former gets the choice of captain seats in the top-spec variant. Tata Safari Engine and Transmission: It is powered by the Harrier’s 2.0-litre diesel engine (170PS/350Nm), paired with a 6-speed manual and an optional 6-speed automatic. Going forward, Tata could also provide the SUV with a 1.5-litre turbo-petrol unit and an AWD.  Tata Safari Features: The Safari gets an 8.8-inch touchscreen infotainment system, iRA connected car tech, a 9-speaker JBL sound system, a panoramic sunroof, and a 6-way powered driver seat. It also gets cruise control, auto AC with the second and third-row vents, mood lighting, tyre pressure monitoring, and premium leatherette upholstery (for the dual-tone cabin). Tata Safari Safety: The new Safari gets disc brakes all around, an electronic parking brake with auto hold, traction control, up to six airbags, rollover mitigation, and corner stability control. Tata Safari Rivals: It rivals the Mahindra XUV500, MG Hector Plus, Hyundai Alcazar, and the Mahindra XUV700."
  ],

  "ProsCons": {
    "pros": [
      "Comfortable and spacious seating for 7",
      "Impressive ride comfort",
      "Cabin feels premium"
    ],
    "cons": [
      "Missing some modern day features",
      "White upholstery gets dirty easily",
      "Captain seats are narrow"
    ]
  },
  "Colorss": {
    "color1": ["Royal Blue", "bg-blue-800"],
    "color2": ["Daytona Grey", "bg-gray-700"],
    "color3": ["Orcus White", "bg-white-600"],
    "color4": ["Tropical Mist", "bg-blue-200"]
  },

  "ComparisionCar": {
    "comparisioncar1": [
      "₹ 14.30 Lakh Onwards",
      "14.63 to 16.35 kmpl",
      "1956 cc",
      "Manual & Automatic (Torque Converter)",
      "Diesel",
      "5 Seater",
      "4,598 mm L x 1,894 mm W x 1,706 mm H",
      "https://imgd.aeplcdn.com/664x374/n/cw/ec/32958/tata-harrier-right-front-three-quarter58.jpeg?q=85"
    ],
    "comparisioncar2": [
      "₹ 13.18 Lakh onwards",
      "13.96 to 17.41 kmpl",
      "1451 to 1956 cc",
      "Manual & Automatic",
      "Petrol & Diesel",
      "5 Seater",
      "4655 mm in length, 1835 mm in width and 1760 mm in height",
      "https://imgd.aeplcdn.com/664x374/n/cw/ec/52565/hector-exterior-right-front-three-quarter-3.jpeg?q=85"
    ]
  },

  "HighlightedFeatures": {
    "feature1": [
      "https://stimg.cardekho.com/images/carinteriorimages/930x620/Maruti/Baleno/6778/1615985207322/interior-image-209.jpg?imwidth=480",
      "Stylish Interiors",
      ""
    ],
    "feature2": [
      "https://image.shutterstock.com/image-photo/car-door-lock-knob-children-260nw-1514746379.jpg",
      "Rear Door Child Lock",
      ""
    ],
    "feature3": [
      "https://stimg.cardekho.com/images/carinteriorimages/630x420/Maruti/Alto-800/7075/1594805410865/airbags-94.jpg?tr=w-360",
      "2 Airbags",
      ""
    ]
  },
  "faqs": {
    "question1": [
      "What is the on road price of Safari?",
      "The on-road price of Safari in Delhi starts at ‎₹ 18.06 Lakh and goes upto ‎₹ 26.34 Lakh. The on road price is made up of ex-showroom price, RTO registration, road tax and insurance amount."
    ],
    "question2": [
      "Which car is better between Safari and Harrier?",
      "Safari price starts at ₹ 14.99 Lakh ex-showroom and It comes with 1956 cc engine. Whereas Harrier price starts at ₹ 14.39 Lakh ex-showroom and It comes with 1956 cc engine."
    ],
    "question3": [
      "What is the mileage of Tata Safari?",
      "The Tata Safari mileage is 14.08 - 16.14 kmpl."
    ]
  },

  "articles": {
    "article1": [
      "/kushaq.png",
      "Rath Yatra 2021: About 60 Skoda Kushaq SUVs To Be Delivered In Ahmedabad"
    ],
    "article2": [
      "/kushaq.png",
      "Rath Yatra 2021: About 60 Skoda Kushaq SUVs To Be Delivered In Ahmedabad"
    ],
    "article3": [
      "/kushaq.png",
      "Rath Yatra 2021: About 60 Skoda Kushaq SUVs To Be Delivered In Ahmedabad"
    ]
  },

  "SimilarCars": {},
  "ThatBrandCars": {
    "car1": [
      "https://imgd.aeplcdn.com/664x374/n/cw/ec/41645/tata-nexon-right-front-three-quarter3.jpeg?q=85",
      "Nexon",
      "₹ 7.20 Lakh onwards"
    ],
    "car2": [
      "https://imgd.aeplcdn.com/664x374/n/cw/ec/32597/tata-altroz-right-front-three-quarter20.jpeg?q=85",
      "Altroz",
      "₹ 5.80 Lakh onwards"
    ],
    "car3": [
      "https://imgd.aeplcdn.com/664x374/n/cw/ec/40027/safari-exterior-right-front-three-quarter-2.jpeg?q=85",
      "Safari",
      "₹ 14.99 Lakh onwards"
    ],
    "car4": [
      "https://imgd.aeplcdn.com/664x374/n/cw/ec/32958/tata-harrier-right-front-three-quarter58.jpeg?q=85",
      "Harrier",
      "₹ 14.30 Lakh onwards"
    ],
    "car5": [
      "https://imgd.aeplcdn.com/664x374/n/cw/ec/39345/tiago-exterior-right-front-three-quarter-6.jpeg?q=85",
      "Tiago",
      "₹ 5.00 Lakh onwards"
    ],
    "car6": [
      "https://imgd.aeplcdn.com/664x374/n/cw/ec/41160/tata-tigor-right-front-three-quarter3.jpeg?q=85",
      "Tigor",
      "₹ 5.60 Lakh onwards"
    ],
    "car7": [
      "https://imgd.aeplcdn.com/664x374/n/cw/ec/42611/tata-nexon-ev-right-front-three-quarter6.jpeg?q=85",
      "Nexon EV",
      "₹ 13.99 Lakh onwards"
    ],
    "car8": [
      "https://imgd.aeplcdn.com/664x374/n/cw/ec/40451/tata-tigor-ev-exterior-1.jpeg?q=85",
      "Tigor EV",
      "₹ 10.58 Lakh onwards"
    ],
    "car9": [
      "https://imgd.aeplcdn.com/664x374/n/cw/ec/99113/tiago-nrg-bs6-exterior-right-front-three-quarter.jpeg?isig=0&q=85",
      "Tiago NRG",
      "₹ 6.57 Lakh onwards"
    ]
  },

  "UpcommingCarBrand": {
    "car1": [
      "https://imgd.aeplcdn.com/664x374/cw/ec/39015/Tata-H2X-Exterior-170093.jpg?wm=0&q=85",
      "HBX",
      "₹ 5.00 - 8.00 Lakh"
    ],
    "car2": [
      "https://imgd.aeplcdn.com/664x374/cw/ec/40453/Tata-Tiago-EV-Exterior-169932.jpg?wm=0&q=85",
      "Tiago EV",
      "₹ 5.00 - 7.00 Lakh"
    ],
    "car3": [
      "https://imgd.aeplcdn.com/664x374/n/cw/ec/46800/tata-altroz-ev-left-side-view5.jpeg?q=85",
      "Altroz EV",
      "₹ 12.00 - 15.00 Lakh"
    ]
  },
  "Thatbrandmobile": [
    {
      "ccard": [
        "https://i.ibb.co/W6RcyRP/nexon1630474668.jpg",
        "Nexon",
        "₹ 7.20 Lakh onwards"
      ]
    },
    {
      "ccard": [
        "https://i.ibb.co/Q9f2btR/altroz1630474667.jpg",
        "Altroz",
        "₹ 5.80 Lakh onwards"
      ]
    },
    {
      "ccard": [
        "https://i.ibb.co/FVKPS2R/safari1630474668.jpg",
        "Safari",
        "₹ 14.99 Lakh onwards"
      ]
    },
    {
      "ccard": [
        "https://i.ibb.co/WDjF7dt/Harrier1630474668.jpg",
        "Harrier",
        "₹ 14.30 Lakh onwards"
      ]
    },
    {
      "ccard": [
        "https://i.ibb.co/gZXxN6Q/tiago1630474669.jpg",
        "Tiago",
        "₹ 5.00 Lakh onwards"
      ]
    },
    {
      "ccard": [
        "https://i.ibb.co/PzNwF9b/tigor1630474669.jpg",
        "Tigor",
        "₹ 5.60 Lakh onwards"
      ]
    },
    {
      "ccard": [
        "https://i.ibb.co/mSQYVL1/nexonev1630474668.jpg",
        "Nexon EV",
        "₹ 13.99 Lakh onwards"
      ]
    },
    {
      "ccard": [
        "https://i.ibb.co/0B6hcv8/tigorev1630474669.jpg",
        "Tigor EV",
        "₹ 10.58 Lakh onwards"
      ]
    },
    {
      "ccard": [
        "https://i.ibb.co/zH627Cm/tiagonrg1630474669.jpg",
        "Tiago NRG",
        "₹ 6.57 Lakh onwards"
      ]
    }
  ],

  "ComparisionCarMobile": [
    {
      "ccard": [
        "Dzire",
        "₹ 5.98 Lakh onwards",
        "23.26 to 24.12 kmpl",
        "1197 cc",
        "Manual & Automatic",
        "Petrol",
        "5 Seater",
        "3,995 mm L x 1,735 mm W x 1,515 mm H",
        "https://imgd.aeplcdn.com/664x374/n/cw/ec/45691/marutisuzuki-dzire-right-front-three-quarter8.jpeg?q=85",

        "Aura",
        "₹ 6.00 Lakh onwards",
        "20 to 28 kmpl",
        "998 to 1197 cc",
        "Manual & Automatic AMT",
        "Petrol & Diesel",
        "5 Seater",
        "3,995 mm L x 1,680 mm W x 1,520 mm H",
        "https://imgd.aeplcdn.com/664x374/n/cw/ec/41652/aura-exterior-right-front-three-quarter-54.jpeg?q=85"
      ]
    },
    {
      "ccard": [
        "Aura",
        "₹ 6.00 Lakh onwards",
        "20 to 28 kmpl",
        "998 to 1197 cc",
        "Manual & Automatic AMT",
        "Petrol & Diesel",
        "5 Seater",
        "3,995 mm L x 1,680 mm W x 1,520 mm H",
        "https://imgd.aeplcdn.com/664x374/n/cw/ec/41652/aura-exterior-right-front-three-quarter-54.jpeg?q=85",
        "Dzire",
        "₹ 5.98 Lakh onwards",
        "23.26 to 24.12 kmpl",
        "1197 cc",
        "Manual & Automatic",
        "Petrol",
        "5 Seater",
        "3,995 mm L x 1,735 mm W x 1,515 mm H",
        "https://imgd.aeplcdn.com/664x374/n/cw/ec/45691/marutisuzuki-dzire-right-front-three-quarter8.jpeg?q=85"
      ]
    }
  ],

  "CarInfo": {
    "CompanyName": "Tata",
    "CarName": "Tata Safari",
    "OnlyName": ["Safari"],
    "Price": ["₹ 14.99 Lakh"],
    "TopPic": ["https://i.ibb.co/qs1V2Xy/safari.webp"],
    "ThumPic": "https://i.ibb.co/FVKPS2R/safari1630474668.jpg",
    "CarFullName": ["Tata Safari"]
  }
}
